QuBuilders/__init__.py
QuBuilders/__main__.py
QuBuilders/.github/workflows/python-package.yml
QuBuilders/NchTan/__init__.py
QuBuilders/NchTan/form.py
QuBuilders/NchTan/formd.py
QuBuilders/NchTan/quseq.py
QuBuilders/generators/__init__.py
QuBuilders/generators/stament/Asghar_S.py
QuBuilders/generators/stament/Mode_S.py
QuBuilders/generators/stament/Rostam_S.py
QuBuilders/generators/stament/__init__.py
QuBuilders/generators/stament/checker.py
QuBuilders/quloaders/__init__.py
QuBuilders/quloaders/csv_loader.py
QuBuilders/quloaders/json_loader.py
QuBuilders/quwriter/__init__.py
QuBuilders/quwriter/csv_writer.py
QuBuilders/quwriter/json_writer.py
QuBuilders/quwriter/type_checker.py
qubuilders-0.0.6.dist-info/METADATA
qubuilders-0.0.6.dist-info/WHEEL
qubuilders-0.0.6.dist-info/licenses/LICENSE
qubuilders-0.0.6.dist-info/RECORD
