Metadata-Version: 2.1
Name: QuBuilders
Version: 0.0.6
Summary: a pakage that help you to make n choice questions faster
Project-URL: Homepage, https://github.com/AmirrezaZahraei1387/QuBu
Project-URL: Bug Tracker, https://github.com/AmirrezaZahraei1387/QuBu/issues
Author-email: Amirrza Zahraei <amir.reza.zahraei@gmail.com>
License-File: LICENSE
Classifier: License :: OSI Approved :: MIT License
Classifier: Operating System :: OS Independent
Classifier: Programming Language :: Python :: 3
Requires-Python: >=3.7
